mylib/__init__.py
mylib/pakage1/__init__.py
mylib/pakage1/module1.py
mylib/pakage1/module2.py
mylib/pakage2/__init__.py
mylib/pakage2/module3.py
skttejapy-0.1.0.dist-info/METADATA
skttejapy-0.1.0.dist-info/WHEEL
skttejapy-0.1.0.dist-info/top_level.txt
skttejapy-0.1.0.dist-info/RECORD
