Metadata-Version: 2.4
Name: skttejapy
Version: 0.1.0
Summary: A short description of what your library does
Author-email: skt <pythonman077@gmail.com>
Project-URL: Homepage, https://github.com/pythonman007
Project-URL: Repository, https://github.com/pythonman007/basic-of-web-development
Requires-Python: >=3.8
